xerializer/__init__.py
xerializer/_argparse.py
xerializer/_registered.py
xerializer/abstract_type_serializer.py
xerializer/builtin_plugins.py
xerializer/cli_builder.py
xerializer/datetime_plugins.py
xerializer/decorator.py
xerializer/enum_plugin.py
xerializer/generic_plugin.py
xerializer/serializer.py
xerializer/utils.py
xerializer/numpy_plugins/__init__.py
xerializer/numpy_plugins/_helpers.py
xerializer/numpy_plugins/array.py
xerializer/numpy_plugins/base.py
xerializer/numpy_plugins/numpy_as_bytes_serializers.py
xerializer/numpy_plugins/numpy_serializers.py
xerializer-0.1.0.dist-info/METADATA
xerializer-0.1.0.dist-info/WHEEL
xerializer-0.1.0.dist-info/top_level.txt
xerializer-0.1.0.dist-info/RECORD
