Metadata-Version: 2.1
Name: xerializer
Version: 0.1.0
Home-page: https://github.com/zepedaj/xerializer
Author: Joaquin Zepeda
Requires-Dist: numpy
Requires-Dist: pytz
Requires-Dist: hydra-core
Requires-Dist: frozendict
Requires-Dist: jztools
